{
	"backgroundColor": 6710886,
	"doc.openedDocs": [
		"ui://hbq27te38gel3k",
		"ui://hbq27te38gel2c",
		"ui://hbq27te38gel4v",
		"ui://hbq27te38gel4w",
		"ui://hbq27te38gel42",
		"ui://hbq27te38gel41",
		"ui://hbq27te38gel40",
		"ui://hbq27te38gel17",
		"ui://hbq27te38gel1f",
		"ui://hbq27te38gel60",
		"ui://hbq27te38gel46"
	],
	"libview.expandedNodes": [
		"hbq27te3",
		"/",
		"hbq27te3",
		"/ui/"
	],
	"auxline2": true,
	"canvasColor": 10066329,
	"libview.firstColumnWidth": 283,
	"auxline1": true,
	"libview.twoColumn": false,
	"libview.currentGroup": "",
	"doc.activeDoc": "ui://hbq27te38gel4w"
}