{"1":{"id":1,"name":"\u693F\u5229\u5C0F\u59D0","model_path":"chunli","icon_path":"ui://eyd6k7hgg2frm","reward_type":3,"reward_value":16,"reward_coin_value":[100,200],"coin_icon":"ui://eyd6k7hgo9oq1e","unlock_type":2,"unlock_value":3,"code":"110","avliable":true,"offset":[0.0,0.0,-3.0],"rotation":[0.0,180.0,0.0],"scale":[4.0,4.0,4.0]},"2":{"id":2,"name":"\u7F8E\u4E3D\u5C11\u5973","model_path":"meishaonv","icon_path":"ui://eyd6k7hgg2frq","reward_type":3,"reward_value":17,"reward_coin_value":[100,200],"coin_icon":"ui://eyd6k7hgo9oq1e","unlock_type":3,"unlock_value":3,"code":"0","avliable":true,"offset":[0.0,0.0,-3.0],"rotation":[0.0,180.0,0.0],"scale":[4.0,4.0,4.0]},"3":{"id":3,"name":"\u4F6C\u5566\u4E3D\u5F71","model_path":"laola","icon_path":"ui://eyd6k7hgg2frp","reward_type":3,"reward_value":18,"reward_coin_value":[100,200],"coin_icon":"ui://eyd6k7hgo9oq1e","unlock_type":2,"unlock_value":3,"code":"678","avliable":true,"offset":[0.0,0.0,-3.0],"rotation":[0.0,180.0,0.0],"scale":[4.0,4.0,4.0]},"4":{"id":4,"name":"\u5C0F\u4E11\u5973\u58EB","model_path":"xiaochou","icon_path":"ui://eyd6k7hgg2fro","reward_type":3,"reward_value":19,"reward_coin_value":[100,200],"coin_icon":"ui://eyd6k7hgo9oq1e","unlock_type":3,"unlock_value":3,"code":"0","avliable":true,"offset":[0.0,0.0,-3.0],"rotation":[0.0,180.0,0.0],"scale":[4.0,4.0,4.0]}}
